{
  "id": "2049175",
  "question": "Bitcoin Up or Down - April 22, 11:40PM-11:45PM ET",
  "conditionId": "0x890c8feda11e3c97ce29d8e22cb064f66f6d41420507e8c920817277b37bf3d6",
  "slug": "btc-updown-5m-1776915600",
  "resolutionSource": "https://data.chain.link/streams/btc-usd",
  "endDate": "2026-04-23T03:45:00Z",
  "liquidity": "19223.6835",
  "startDate": "2026-04-22T03:48:01.327951Z",
  "image": "https://polymarket-upload.s3.us-east-2.amazonaws.com/BTC+fullsize.png",
  "icon": "https://polymarket-upload.s3.us-east-2.amazonaws.com/BTC+fullsize.png",
  "description": "This market will resolve to \"Up\" if the Bitcoin price at the end of the time range specified in the title is greater than or equal to the price at the beginning of that range. Otherwise, it will resolve to \"Down\".\nThe resolution source for this market is information from Chainlink, specifically the BTC/USD data stream available at https://data.chain.link/streams/btc-usd.\nPlease note that this market is about the price according to Chainlink data stream BTC/USD, not according to other sources or spot markets.",
  "outcomes": "[\"Up\", \"Down\"]",
  "outcomePrices": "[\"0.505\", \"0.495\"]",
  "volume": "252.48392",
  "active": true,
  "closed": false,
  "marketMakerAddress": "",
  "createdAt": "2026-04-22T03:46:54.325955Z",
  "updatedAt": "2026-04-23T03:35:04.243225Z",
  "new": false,
  "featured": false,
  "archived": false,
  "restricted": true,
  "groupItemThreshold": "0",
  "questionID": "0x83c1a3be0741dd9441e3a20776eb01a6e6a848d168f9059b9a735797835bbeb0",
  "enableOrderBook": true,
  "orderPriceMinTickSize": 0.01,
  "orderMinSize": 5,
  "volumeNum": 252.48392,
  "liquidityNum": 19223.6835,
  "endDateIso": "2026-04-23",
  "startDateIso": "2026-04-22",
  "hasReviewedDates": true,
  "volume24hr": 252.48392,
  "volume1wk": 252.48392,
  "volume1mo": 252.48392,
  "volume1yr": 252.48392,
  "clobTokenIds": "[\"60184353021509783719380374577836550394950996423304818821387033203291503028408\", \"27291183154210556617497174786766198514164686351426545752807179524777139968026\"]",
  "volume24hrClob": 252.48392,
  "volume1wkClob": 252.48392,
  "volume1moClob": 252.48392,
  "volume1yrClob": 252.48392,
  "volumeClob": 252.48392,
  "liquidityClob": 19223.6835,
  "makerBaseFee": 1000,
  "takerBaseFee": 1000,
  "acceptingOrders": true,
  "negRisk": false,
  "ready": false,
  "funded": false,
  "acceptingOrdersTimestamp": "2026-04-22T03:46:58Z",
  "cyom": false,
  "competitive": 0.9999750006249843,
  "pagerDutyNotificationEnabled": false,
  "approved": true,
  "rewardsMinSize": 50,
  "rewardsMaxSpread": 4.5,
  "spread": 0.01,
  "lastTradePrice": 0.51,
  "bestBid": 0.5,
  "bestAsk": 0.51,
  "automaticallyActive": true,
  "clearBookOnStart": false,
  "showGmpSeries": false,
  "showGmpOutcome": false,
  "manualActivation": false,
  "negRiskOther": false,
  "umaResolutionStatuses": "[]",
  "pendingDeployment": false,
  "deploying": false,
  "rfqEnabled": false,
  "eventStartTime": "2026-04-23T03:40:00Z",
  "holdingRewardsEnabled": false,
  "feesEnabled": true,
  "requiresTranslation": false,
  "makerRebatesFeeShareBps": 10000,
  "feeType": "crypto_fees_v2",
  "feeSchedule": {
    "exponent": 1,
    "rate": 0.072,
    "takerOnly": true,
    "rebateRate": 0.2
  }
}